{"url": "https://otomotif.kompas.com/read/2016/05/15/103505015/Honda.Rancang.Generasi.Baru.Brio", "title": "Honda Rancang Generasi Baru Brio", "author": "Ghulam Muhammad Nayazri", "date": "Kompas.com - 15/05/2016, 10:35 WIB", "detail_text": "\n                    New Delhi, KompasOtomotif \u2013 Honda Mobil India mengabarkan sedang dalam pengembangan produk generasi terbaru Honda Brio. Produk ini natinya tidak hanya untuk konsumen India, tetapi juga untuk pasar global.\n\"Kami sedang dalam proses mengembangkan generasi Brio berikutnya. Ini adalah model global dan tidak eksklusif untuk India. Honda R&amp;D sedang mengembangkan beberapa platform baru,\u201d ujar Mr. Yolchiro Ueno, Presiden dan CEO Honda Mobil India, seperti dilansir Motorbeam.com, Sabtu (14/5/2016).\nUeno melanjutkan, platform ini utamanya dikembangkan di Thailand, namun bekerja sama dengan Honda Jepang dan India. \u00a0Pihak Honda India tidak banyak memberikan informasi, namun dikatakan bahwa pengembangan yang sedang dikerjakan lebih kepada standar keselamatan dan struktur utuh kendaraan.\nPihak Honda India mengharapkan, Honda Brio generasi terbaru ini akan mulai diproduksi pada Februari 2018, \u00a0berlokasi di pabrik Greater Noida, India. Pengembangan bersama ketiga basis produksi tersebut (Thailand, Jepang, India), ditujukan untuk mengakomodasi permintaan konsumen seluruh dunia.\nDi Indonesia, Honda Brio, khususnya Brio RS, yang baru saja mengalami penyegaran tampang dan teknologi CVT. Bukan hanya Brio RS, naik kasta juga diberikan kepada \u201cmobil murah\u201d Honda Brio Satya, di pameran Indonesia International Motor Show (IIMS) 2016.                    \n\n                    \n                "}