{"url": "https://nasional.kompas.com/read/2020/05/12/20561271/doni-monardo-jika-kurva-tak-menurun-tak-mungkin-psbb-dilonggarkan", "title": "Doni Monardo: Jika Kurva Tak Menurun, Tak Mungkin PSBB Dilonggarkan", "author": "Rakhmat Nur Hakim", "date": "Kompas.com - 12/05/2020, 20:56 WIB", "detail_text": "\n                    JAKARTA, KOMPAS.com - Ketua Gugus Tugas Percepatan Penanganan  Covid-19  Doni Monardo memastikan tak ada pelonggaran Pembatasan Sosial Berskala Besar (PSBB) bila kurva penambahan kasus harian di suatu daerah belum menurun.\nIa memastikan pelonggaran PSBB akan mempertimbangkan faktor epidemologi seperti laju kurva penambahan kasus harian.\n\"Kalau daerah belum menunjukkan kurva menurun apalagi kurva melandai, maka tidak mungkin daerah itu diberikan kesempatan untuk lakukan pelonggaran. Artinya apa? Statusnya masih tetap tidak boleh kendor, justru harus meningkat kembali,\" kata Doni melalui video conference, Selasa (12/5/2020).\nBaca juga: Strategi Ini Membuat Gubernur Bali Yakin Daerahnya Bisa Jadi yang Pertama Bebas Covid-19\r\n        \r\n            googletag.cmd.push(function() { googletag.display('div-gpt-ad-974648810682144181-5112'); });\r\n        \r\n    \nSelain itu pemerintah juga melihat tingkat kepatuhan masyarakat sebagai bahan pertimbangan untuk melonggarkan PSBB.\nSemakin rendah tingkat kepatuhan masyarakatnya, semakin kecil pula kemungkinan pelomggaran PSBB di suatu daerah.\nKarenanya, Doni mengatakan, pemerintah melalui Gugus Tugas akan melihat kurva penambahan kasus harian dipadukan dengan tingkat kepatuhan masyarakat untuk menyetujui pelonggaran PSBB.\nBaca juga: Doni Monardo Sadar Warga 45 Tahun ke Bawah Bisa Jadi Carrier Covid-19\nDoni pun menambahkan koordinasi antara pemerintah pusat dan daerah juga harus sinkron ketika nantinya memutuskan pelonggaran PSBB.\n\"Ini penting sekali. Jangan sampai nanti diberikan pelonggaran ternyata ada penolakan. Demikian juga mungkin dari daerah memutuskan untuk minta pelonggaran atas inisiatif sendiri, ternyata pusat melihat belum waktunya. Jadi koordinasi pusat daerah ini jadi prioritas kami,\" lanjut Doni.                "}